gotify_message/__init__.py
gotify_message/gotify_notification.py
gotify_message-0.1.0.dist-info/LICENSE
gotify_message-0.1.0.dist-info/METADATA
gotify_message-0.1.0.dist-info/WHEEL
gotify_message-0.1.0.dist-info/top_level.txt
gotify_message-0.1.0.dist-info/RECORD
