Metadata-Version: 2.1
Name: gotify-message
Version: 0.1.0
Summary: Python module to push messages to gotify server
Home-page: https://github.com/pbubas/gotify_message
Author: Przemek Bubasr
Author-email: bubasenator@gmail.com
Project-URL: Bug Tracker, https://github.com/pbubas/gotify_message/issues
Classifier: Programming Language :: Python :: 3
Classifier: License :: OSI Approved :: MIT License
Classifier: Operating System :: OS Independent
Requires-Python: >=3.6
License-File: LICENSE
Requires-Dist: requests (>=2.25.1)
